LICENSE
MANIFEST.in
README.md
setup.cfg
setup.py
docassemble.helloworld.egg-info/PKG-INFO
docassemble.helloworld.egg-info/SOURCES.txt
docassemble.helloworld.egg-info/dependency_links.txt
docassemble.helloworld.egg-info/not-zip-safe
docassemble.helloworld.egg-info/top_level.txt
docassemble/helloworld/__init__.py
docassemble/helloworld/data/questions/hello.yml
docassemble/helloworld/data/sources/README.md
docassemble/helloworld/data/static/README.md
docassemble/helloworld/data/static/coins36.png
docassemble/helloworld/data/static/datereplace.js
docassemble/helloworld/data/static/png.png
docassemble/helloworld/data/templates/README.md
docassemble/helloworld/data/templates/hello_planet.docx