Metadata-Version: 2.2
Name: docassemble.helloworld
Version: 6.9
Summary: A docassemble extension.
Home-page: https://docassemble.org
Author: Jonathan Pyle
Author-email: jhpyle@gmail.com
License: The MIT License (MIT)
License-File: LICENSE
Dynamic: author
Dynamic: author-email
Dynamic: description
Dynamic: description-content-type
Dynamic: home-page
Dynamic: license
Dynamic: summary
